setup.py
pwtools/__init__.py
pwtools/pwcheck.py
pwtools/pwgen.py
pwtools/wordset.py
pwtools.egg-info/PKG-INFO
pwtools.egg-info/SOURCES.txt
pwtools.egg-info/dependency_links.txt
pwtools.egg-info/top_level.txt