Metadata-Version: 1.0
Name: pwtools
Version: 0.4
Summary: Password generation and security checking
Home-page: http://alastairs-place.net/pwtools
Author: Alastair Houghton
Author-email: alastair@alastairs-place.net
License: MIT License
Platform: UNKNOWN
Classifier: Development Status :: 4 - Beta
Classifier: Intended Audience :: Developers
Classifier: License :: OSI Approved :: MIT License
Classifier: Topic :: System
